Workbook

Sheet Summary
A1: Genoa - New York | A321XLR business case
A2: Avia Solutions | catchment - demand - economics - seasonality - fleet
A4: Headline (central planning case)
A5: Annual profit | B5: ='Route P&L'!$B$39 -> 9158339.4
A6: Route margin | B6: ='Route P&L'!$B$37 -> 0.15321681
A7: Breakeven load factor | B7: ='Route P&L'!$B$38 -> 0.6885614
A8: Directional demand (each way) | B8: ='Route P&L'!$B$4 -> 93260.509
A10: How it is operated changes the number
A11: Standalone (Genoa-only fleet) | B11: =Fleet!$B$18 -> 5127639.2
A12: Network (fleet kept busy) | B12: =Fleet!$B$17 -> 9158339.4
A13: The headline charges ownership at a fully-utilised rate, so it is a network number; a single daily Genoa route uses the aircraft 60% and the standalone figure is lower. A seasonal schedule plus winter redeployment is what earns the headline.
A15: The case in one line
A16: Genoa's New York travellers leak to Milan today; a Genoa nonstop repatriates its own catchment.
A17: Fares one-way (2024 Sabre); business fare $1,400 the swing from the old $750; fuel at a $0.90/kg planning price.
A18: Viable across the band; honest planning is circa 15% margin, with fuel, seasonality and fleet the watchpoints.
A20: Indicative, for directional guidance only. Built on generic published assumptions, not any airline's actual LOPA, MTOW, contract terms or internal P&L. Catchment, demand and fares anchored to the validated Genoa-New York case; actual results will differ.

Sheet Inputs
A1: Genoa - New York | inputs (blue = change me)
A3: Commercial inputs
A4: Capture of leaked catchment | B4: 0.65
A5: Frequency (each way / week) | B5: 7
A6: Planning load-factor cap | B6: 0.85
A7: Economy fare, one-way ($) | B7: 345
A8: Business fare, one-way ($) | B8: 1400
A9: Jet fuel price ($/kg) | B9: 0.9
A10: Economy share of demand | B10: 0.8
A11: Market adjustment (1.0 = neutral) | B11: 1
A13: Catchment & demand (from the QSI chain)
A14: Catchment population | B14: 19536487
A15: New York O&D market (Sabre 2024) | B15: 828760.74
A16: Genoa natural NY catchment | B16: 138608.18
A17: Carried by Genoa today | B17: 9043.41
A19: Aircraft & cost constants (A321XLR, validated module)
A20: Economy seats | B20: 162
A21: Business seats | B21: 20
A22: Fuel burn (kg / block-hour) | B22: 2500
A23: Block hours / turnaround | B23: 18
A24: Annual utilisation (block-hr) | B24: 5425
A25: Blended lease ($/aircraft/month) | B25: 423967
A26: Maintenance ($/turn) | B26: 14740.385
A27: Ownership ($/turn) | B27: 16880.516
A28: Crew ($/turn) | B28: 21600
A29: Insurance ($/turn) | B29: 2156.682
A30: Landing, both ends ($/turn) | B30: 4429
A31: Ground handling ($/turn) | B31: 5871
... A36: Charges recovery ($/pax) | B36: 46.35

Sheet Route P&L
A1: Route P&L | per turnaround and annual (formulas off Inputs)
A3: Demand & load
A4: Directional demand (each way) | B4: =(Inputs!$B$17+(Inputs!$B$16-Inputs!$B$17)*Inputs!$B$4)*Inputs!$B$11 -> 93260.509
A5: Economy load factor | B5: =MIN('Route P&L'!$B$4*Inputs!$B$10/(Inputs!$B$20*Inputs!$B$5*52),Inputs!$B$6) -> 0.85
A6: Business load factor | B6: =MIN('Route P&L'!$B$4*(1-Inputs!$B$10)/(Inputs!$B$21*Inputs!$B$5*52),Inputs!$B$6) -> 0.85
A7: Passengers per turnaround | B7: =2*(Inputs!$B$20*'Route P&L'!$B$5+Inputs!$B$21*'Route P&L'!$B$6) -> 309.4
A9: Revenue ($/turn)
A10: Economy | B10: =2*Inputs!$B$20*'Route P&L'!$B$5*Inputs!$B$7 -> 95013
A11: Business | B11: =2*Inputs!$B$21*'Route P&L'!$B$6*Inputs!$B$8 -> 47600
A12: Cargo | B12: =Inputs!$B$33 -> 7259.84
A13: Net revenue | B13: ='Route P&L'!$B$10+'Route P&L'!$B$11+'Route P&L'!$B$12 -> 149872.84
A14: Charges recovery | B14: =Inputs!$B$36*'Route P&L'!$B$7 -> 14340.69
A15: Gross revenue | B15: ='Route P&L'!$B$13+'Route P&L'!$B$14 -> 164213.53
A17: Cost ($/turn)
A18: Fuel | B18: =Inputs!$B$22*Inputs!$B$23*Inputs!$B$9 -> 40500
A19: Maintenance | B19: =Inputs!$B$26 -> 14740.385
A20: Catering | B20: =Inputs!$B$34*'Route P&L'!$B$7 -> 819.2912
A21: Landing | B21: =Inputs!$B$30 -> 4429
A22: Pax airport charges | B22: =Inputs!$B$35*'Route P&L'!$B$7 -> 15934.1
A23: En-route navigation | B23: =Inputs!$B$32 -> 1134.999
A24: Ground handling | B24: =Inputs!$B$31 -> 5871
A25: Variable cost | B25: ='Route P&L'!$B$18+'Route P&L'!$B$19+'Route P&L'!$B$20+'Route P&L'!$B$21+'Route P&L'!$B$22+'Route P&L'!$B$23+'Route P&L'!$B$24 -> 83428.775
A26: Ownership | B26: =Inputs!$B$27 -> 16880.516
A27: Insurance | B27: =Inputs!$B$29 -> 2156.682
A28: Crew | B28: =Inputs!$B$28 -> 21600
A29: Direct fixed | B29: ='Route P&L'!$B$26+'Route P&L'!$B$27+'Route P&L'!$B$28 -> 40637.198
A30: Admin (5% net) | B30: =0.05*'Route P&L'!$B$13 -> 7493.642
A31: Sales (5% net) | B31: =0.05*'Route P&L'!$B$13 -> 7493.642
A32: Indirect fixed | B32: ='Route P&L'!$B$30+'Route P&L'!$B$31 -> 14987.284
A33: Total cost | B33: ='Route P&L'!$B$25+'Route P&L'!$B$29+'Route P&L'!$B$32 -> 139053.26
A35: Result
A36: Profit per turnaround | B36: ='Route P&L'!$B$15-'Route P&L'!$B$33 -> 25160.273
A37: Margin | B37: ='Route P&L'!$B$36/'Route P&L'!$B$15 -> 0.15321681
A38: Breakeven load factor | B38: =((Inputs!$B$20*'Route P&L'!$B$5+Inputs!$B$21*'Route P&L'!$B$6)/(Inputs!$B$20+Inputs!$B$21))*(('Route P&L'!$B$33-('Route P&L'!$B$20+'Route P&L'!$B$22+'Route P&L'!$B$32))/('Route P&L'!$B$15-('Route P&L'!$B$20+'Route P&L'!$B$22+'Route P&L'!$B$32))) -> 0.6885614
A39: Annual profit | B39: ='Route P&L'!$B$36*Inputs!$B$5*52 -> 9158339.4
A40: Annual passengers | B40: ='Route P&L'!$B$7*Inputs!$B$5*52 -> 112621.6

Sheet Fleet
A1: Fleet utilisation & redeployment
A3: The headline charges ownership at a fully-utilised rate
A4: Annual block hours | B4: =Inputs!$B$5*52*Inputs!$B$23 -> 6552
A5: Aircraft required | B5: =CEILING(Fleet!$B$4/Inputs!$B$24,1) -> 2
A6: Per-aircraft utilisation | B6: =Fleet!$B$4/Fleet!$B$5 -> 3276
A7: Utilisation vs full | B7: =Fleet!$B$6/Inputs!$B$24 -> 0.60387097
A8: Spare block hours / year | B8: =Fleet!$B$5*Inputs!$B$24-Fleet!$B$4 -> 4298
A9: Spare rotations / year | B9: =Fleet!$B$8/Inputs!$B$23 -> 238.77778
A11: Ownership recovery
A12: Ownership charged (annual) | B12: =(Inputs!$B$27/Inputs!$B$23)*Fleet!$B$4 -> 6144507.9
A13: True cost if dedicated | B13: =Fleet!$B$5*Inputs!$B$25*12 -> 10175208
A14: Standalone ownership gap | B14: =Fleet!$B$13-Fleet!$B$12 -> 4030700.1
A16: What the headline assumes
A17: Network headline (fleet busy) | B17: ='Route P&L'!$B$39 -> 9158339.4
A18: Standalone (Genoa-only fleet) | B18: =Fleet!$B$17-Fleet!$B$14 -> 5127639.2

Sheet Seasonality
A1: Seasonality | leisure profile (assumption pending monthly Sabre pull)
A3: Month | B3: Days | C3: Demand index | D3: Monthly demand | E3: Flat-daily LF | F3: Seasonal turns
A4: Jan | B4: 31 | C4: 0.527 | D4: ='Route P&L'!$B$4*(B4/365)*C4 -> 4174.2382 | E4: =MIN(D4/((Inputs!$B$20+Inputs!$B$21)*B4),Inputs!$B$6) -> 0.7398508 | F4: =MAX(MIN(B4,CEILING(D4/((Inputs!$B$20+Inputs!$B$21)*Inputs!$B$6),1)),0.5*B4) -> 27
A5: Feb | B5: 28 | C5: 0.448 | D5: ='Route P&L'!$B$4*(B5/365)*C5 -> 3205.0954 | E5: =MIN(D5/((Inputs!$B$20+Inputs!$B$21)*B5),Inputs!$B$6) -> 0.62894337 | F5: =MAX(MIN(B5,CEILING(D5/((Inputs!$B$20+Inputs!$B$21)*Inputs!$B$6),1)),0.5*B5) -> 21
A6: Mar | B6: 31 | C6: 0.701 | D6: ='Route P&L'!$B$4*(B6/365)*C6 -> 5552.4497 | E6: =MIN(D6/((Inputs!$B$20+Inputs!$B$21)*B6),Inputs!$B$6) -> 0.85 | F6: =MAX(MIN(B6,CEILING(D6/((Inputs!$B$20+Inputs!$B$21)*Inputs!$B$6),1)),0.5*B6) -> 31
A7: Apr | B7: 30 | C7: 1.173 | D7: ='Route P&L'!$B$4*(B7/365)*C7 -> 8991.3351 | E7: =MIN(D7/((Inputs!$B$20+Inputs!$B$21)*B7),Inputs!$B$6) -> 0.85 | F7: =MAX(MIN(B7,CEILING(D7/((Inputs!$B$20+Inputs!$B$21)*Inputs!$B$6),1)),0.5*B7) -> 30
A8: May | B8: 31 | C8: 1.128 | D8: ='Route P&L'!$B$4*(B8/365)*C8 -> 8934.6123 | E8: =MIN(D8/((Inputs!$B$20+Inputs!$B$21)*B8),Inputs!$B$6) -> 0.85 | F8: =MAX(MIN(B8,CEILING(D8/((Inputs!$B$20+Inputs!$B$21)*Inputs!$B$6),1)),0.5*B8) -> 31
A9: Jun | B9: 30 | C9: 1.264 | D9: ='Route P&L'!$B$4*(B9/365)*C9 -> 9688.8727 | E9: =MIN(D9/((Inputs!$B$20+Inputs!$B$21)*B9),Inputs!$B$6) -> 0.85 | F9: =MAX(MIN(B9,CEILING(D9/((Inputs!$B$20+Inputs!$B$21)*Inputs!$B$6),1)),0.5*B9) -> 30
A10: Jul | B10: 31 | C10: 1.381 | D10: ='Route P&L'!$B$4*(B10/365)*C10 -> 10938.563 | E10: =MIN(D10/((Inputs!$B$20+Inputs!$B$21)*B10),Inputs!$B$6) -> 0.85 | F10: =MAX(MIN(B10,CEILING(D10/((Inputs!$B$20+Inputs!$B$21)*Inputs!$B$6),1)),0.5*B10) -> 31
A11: Aug | B11: 31 | C11: 1.637 | D11: ='Route P&L'!$B$4*(B11/365)*C11 -> 12966.277 | E11: =MIN(D11/((Inputs!$B$20+Inputs!$B$21)*B11),Inputs!$B$6) -> 0.85 | F11: =MAX(MIN(B11,CEILING(D11/((Inputs!$B$20+Inputs!$B$21)*Inputs!$B$6),1)),0.5*B11) -> 31
A12: Sep | B12: 30 | C12: 1.26 | D12: ='Route P&L'!$B$4*(B12/365)*C12 -> 9658.2117 | E12: =MIN(D12/((Inputs!$B$20+Inputs!$B$21)*B12),Inputs!$B$6) -> 0.85 | F12: =MAX(MIN(B12,CEILING(D12/((Inputs!$B$20+Inputs!$B$21)*Inputs!$B$6),1)),0.5*B12) -> 30
A13: Oct | B13: 31 | C13: 1.047 | D13: ='Route P&L'!$B$4*(B13/365)*C13 -> 8293.0311 | E13: =MIN(D13/((Inputs!$B$20+Inputs!$B$21)*B13),Inputs!$B$6) -> 0.85 | F13: =MAX(MIN(B13,CEILING(D13/((Inputs!$B$20+Inputs!$B$21)*Inputs!$B$6),1)),0.5*B13) -> 31
A14: Nov | B14: 30 | C14: 0.689 | D14: ='Route P&L'!$B$4*(B14/365)*C14 -> 5281.3554 | E14: =MIN(D14/((Inputs!$B$20+Inputs!$B$21)*B14),Inputs!$B$6) -> 0.85 | F14: =MAX(MIN(B14,CEILING(D14/((Inputs!$B$20+Inputs!$B$21)*Inputs!$B$6),1)),0.5*B14) -> 30
A15: Dec | B15: 31 | C15: 0.747 | D15: ='Route P&L'!$B$4*(B15/365)*C15 -> 5916.8044 | E15: =MIN(D15/((Inputs!$B$20+Inputs!$B$21)*B15),Inputs!$B$6) -> 0.85 | F15: =MAX(MIN(B15,CEILING(D15/((Inputs!$B$20+Inputs!$B$21)*Inputs!$B$6),1)),0.5*B15) -> 31
A17: Annual profit at the central case (leisure profile, daily summer):
A18: A nominal flat (plan LF every month) | B18: 9183500
A19: B flat daily, real monthly demand | B19: 7759505
A20: C seasonal schedule (trim winter) | B20: 8868071
A22: Snapshot from seasonality_check.py at the central inputs. A daily-all-year schedule under-fills winter at full cost (B); a seasonal schedule recovers most of it (C). Adjust the demand-index column above and re-run seasonality_check.py for other profiles.

Sheet Scenarios
A1: Scenarios | annual profit ($m), computed from the model
A3: Fuel price down the side, capture across (freq 7, plan LF 85%, fares 345/1400, market neutral)
A4: fuel \ capture | B4: 0.5 | C4: 0.58 | D4: 0.65 | E4: 0.75
A5: 0.68 | B5: 12.8 | C5: 12.8 | D5: 12.8 | E5: 12.8
A6: 0.8 | B6: 10.8 | C6: 10.8 | D6: 10.8 | E6: 10.8
A7: 0.9 | B7: 9.2 | C7: 9.2 | D7: 9.2 | E7: 9.2
A8: 1 | B8: 7.5 | C8: 7.5 | D8: 7.5 | E8: 7.5
A9: 1.1 | B9: 5.9 | C9: 5.9 | D9: 5.9 | E9: 5.9
A12: Market adjustment sensitivity (central case otherwise)
A13: market | B13: annual profit ($m)
A14: 1 | B14: 9.2
A15: 0.93 | B15: 9.2
A16: 0.86 | B16: 9.2
A17: 0.8 | B17: 9.2
A19: Highlighted cell = central planning case (fuel $0.90, capture 65%). Values are a model snapshot; change the Inputs sheet and recalculate to explore other points.

Sheet Assumptions
A1: Assumptions & sources
A3: Catchment & demand
A4: GeoNames population, OSRM road times, catchment calibrated to the Sabre point-of-origin split (SSE 0.0009) | B4: validated
A5: New York O&D split and fares | B5: Sabre ODPOO 2024 (validated)
A6: Fares are one-way; economy $345 entrant yield, business $1,400 | B6: John's entrant-yield judgement, 28 Jun 2026
A7: Economics
A8: Cost stack anchored to Project Maverick (E190 validated 0.3%); A321XLR extrapolated | B8: directional
A9: Jet fuel $0.90/kg through-cycle planning (spot ~$1.10 June 2026, IATA) | B9: planning assumption
A10: Maintenance from Airbus 2024-25 reserve curve | B10: validated
A11: Ownership from appraiser lease/value, A321neo ~$460k/mo (IBA 2025) | B11: directional
A12: Crew $1,200/block-hour (LCC) | B12: judgement, pending citation sweep
A13: GOA / JFK airport charges | B13: INDICATIVE placeholders, not validated tariffs
A14: Seasonality profile (Aug/Feb demand 2.5x) | B14: ASSUMPTION pending monthly Sabre pull
A15: Market
A16: 2026 transatlantic bookings down ~14% Europe-US (Cirium) | B16: demand watchpoint
